LICENSE.txt
MANIFEST.in
README.rst
requirements.example.in
requirements.in
setup.py
Pundler.egg-info/PKG-INFO
Pundler.egg-info/SOURCES.txt
Pundler.egg-info/dependency_links.txt
Pundler.egg-info/requires.txt
Pundler.egg-info/top_level.txt
bin/pundler
pundler/__init__.py