Metadata-Version: 1.1
Name: Pundler
Version: 0.0.2
Summary: An attempt to better manage dependencies in requirements files inspired by Ruby's Gem Bundler
Home-page: https://github.com/steder/pundler
Author: Mike Steder
Author-email: steder@gmail.com
License: UNKNOWN
Platform: UNKNOWN
Classifier: Development Status :: 4 - Beta
Classifier: Operating System :: OS Independent
Classifier: Programming Language :: Python
Classifier: Intended Audience :: Developers
Classifier: License :: OSI Approved :: Apache Software License
Classifier: Topic :: Software Development
Classifier: Topic :: Utilities
